shockdb/__init__.py
shockdb/main.py
shockdb/utils.py
shockdb-0.0.9.dist-info/LICENSE
shockdb-0.0.9.dist-info/METADATA
shockdb-0.0.9.dist-info/WHEEL
shockdb-0.0.9.dist-info/top_level.txt
shockdb-0.0.9.dist-info/RECORD
