Metadata-Version: 2.1
Name: shockdb
Version: 0.0.9
Summary: A python wrapper on lmdb for a simple dbm key-value database
Home-page: https://github.com/mullenkamp/shockdb
Author: Mike Kittridge
Author-email: mullenkamp1@gmail.com
License: Apache
Keywords: shelve dbm lmdb redis
Classifier: Development Status :: 3 - Alpha
Classifier: Intended Audience :: Developers
Classifier: License :: OSI Approved :: Apache Software License
Classifier: Programming Language :: Python :: 3.8
Classifier: Programming Language :: Python :: 3.9
Classifier: Programming Language :: Python :: 3.10
Classifier: Operating System :: OS Independent
Classifier: Topic :: Database
License-File: LICENSE
Requires-Dist: lmdb
Provides-Extra: dev
Requires-Dist: zstandard ; extra == 'dev'
Requires-Dist: lz4 ; extra == 'dev'
Requires-Dist: orjson ; extra == 'dev'
Provides-Extra: test
Requires-Dist: pytest ; extra == 'test'
